cimat/__init__.py
cimat/mtdata.py
cimat/uncertainty_estimator.py
cimat-0.1.2.dist-info/LICENSE
cimat-0.1.2.dist-info/METADATA
cimat-0.1.2.dist-info/NOTICE
cimat-0.1.2.dist-info/WHEEL
cimat-0.1.2.dist-info/RECORD
