Metadata-Version: 2.1
Name: cimat
Version: 0.1.2
Summary: A package for uncertainty quantification of error rates in 1:1 matching tasks.
Author: Riccardo Fogliato
Requires-Python: >=3.9,<4.0
Classifier: Programming Language :: Python :: 3
Classifier: Programming Language :: Python :: 3.9
Classifier: Programming Language :: Python :: 3.10
Classifier: Programming Language :: Python :: 3.11
Classifier: Programming Language :: Python :: 3.12
Requires-Dist: numpy (>=1.25.2,<2.0.0)
Requires-Dist: scikit-learn (>=1.4.2,<2.0.0)
Requires-Dist: scipy (>=1.13.0,<2.0.0)
Requires-Dist: tqdm (>=4.66.2,<5.0.0)
